tools3nm4/__init__.py
tools3nm4/module.py
tools3nm4-0.1.0.dist-info/licenses/LICENSE.txt
tools3nm4-0.1.0.dist-info/METADATA
tools3nm4-0.1.0.dist-info/WHEEL
tools3nm4-0.1.0.dist-info/top_level.txt
tools3nm4-0.1.0.dist-info/RECORD
